mcp_clearml/__init__.py
mcp_clearml/docs.py
mcp_clearml/mcp.py
mcp_clearml/utils.py
mcp_clearml/services/compare.py
mcp_clearml/services/datasets.py
mcp_clearml/services/models.py
mcp_clearml/services/projects.py
mcp_clearml/services/tasks.py
mcp_clearml-0.1.0.dist-info/licenses/LICENSE
mcp_clearml-0.1.0.dist-info/METADATA
mcp_clearml-0.1.0.dist-info/WHEEL
mcp_clearml-0.1.0.dist-info/entry_points.txt
mcp_clearml-0.1.0.dist-info/top_level.txt
mcp_clearml-0.1.0.dist-info/RECORD
