Metadata-Version: 2.4
Name: mcp_clearml
Version: 0.1.0
Summary: MCP server for ClearML
Author-email: Roman <romangodun96@gmail.com>
Maintainer-email: Roman <romangodun96@gmail.com>
License: MIT
Project-URL: bugs, https://github.com/r.godun/mcp_clearml/issues
Project-URL: changelog, https://github.com/r.godun/mcp_clearml/blob/master/changelog.md
Project-URL: homepage, https://github.com/r.godun/mcp_clearml
Requires-Python: >=3.12
License-File: LICENSE
Requires-Dist: clearml~=1.18.0
Requires-Dist: fastmcp~=0.4.0
Provides-Extra: test
Requires-Dist: coverage; extra == "test"
Requires-Dist: pytest; extra == "test"
Requires-Dist: pytest-asyncio; extra == "test"
Requires-Dist: ruff; extra == "test"
Requires-Dist: ty; extra == "test"
Requires-Dist: ipdb; extra == "test"
Dynamic: license-file
